Workbook
Name DiasMes: 'Parámetros'!$B$8
Name Factor25: 'Parámetros'!$B$10
Name Factor35: 'Parámetros'!$B$11
Name HorasDia: 'Parámetros'!$B$9
Name ListaAFP: 'Parámetros'!$A$15:$A$19
Name RMV: 'Parámetros'!$B$4
Name TasaAF: 'Parámetros'!$B$5
Name TasaEsSalud: 'Parámetros'!$B$7
Name TasaONP: 'Parámetros'!$B$6

Sheet Parámetros
A1: SEMANA 9 · PARÁMETROS EDITABLES
A3: Parámetro | B3: Valor | C3: Unidad | D3: Fuente / observación | E3: Consulta
A4: RMV | B4: 1230 | C4: S/ | D4: https://busquedas.elperuano.pe/dispositivo/NL/2559163-1 | E4: 2026-10-26
A5: Asignación familiar | B5: 0.1 | C5: % RMV | D5: https://www.gob.pe/institucion/mtpe/noticias/601761-quienes-tienen-derecho-a-percibir-la-asignacion-familiar | E5: 2026-10-26
A6: ONP | B6: 0.13 | C6: % remuneraciones | D6: https://www.gob.pe/institucion/onp/noticias/1190488-como-saber-si-tu-empleador-esta-pagando-tus-aportes-al-snp | E6: 2026-10-26
A7: EsSalud | B7: 0.09 | C7: % remuneraciones | D7: https://www.sunat.gob.pe/legislacion/oficios/2007/oficios/i0032007.htm | E7: 2026-10-26
A8: Días del mes | B8: 30 | C8: días | D8: Guía sección 4 | E8: 2026-10-26
A9: Horas de jornada | B9: 8 | C9: horas | D9: Guía sección 4 | E9: 2026-10-26
A10: Factor extra 25% | B10: 1.25 | C10: multiplicador | D10: https://www.gob.pe/institucion/sunafil/noticias/1100081-conoce-las-diferencias-entre-trabajo-forzoso-y-trabajo-en-sobretiempo | E10: 2026-10-26
A11: Factor extra 35% | B11: 1.35 | C11: multiplicador | D11: https://www.gob.pe/institucion/sunafil/noticias/1100081-conoce-las-diferencias-entre-trabajo-forzoso-y-trabajo-en-sobretiempo | E11: 2026-10-26
A14: AFP | B14: Fondo | C14: Comisión flujo | D14: Seguro | E14: Fuente
A15: Ejemplo | B15: 0.1 | C15: 0.016 | D15: 0.0135 | E15: Guía: prueba
A16: Habitat (flujo) | B16: 0.1 | C16: 0.0147 | D16: 0.0137 | E16: https://www.sbs.gob.pe/app/spp/empleadores/comisiones_spp/Paginas/comision_prima.aspx
A17: Integra (flujo) | B17: 0.1 | C17: 0.0155 | D17: 0.0137 | E17: https://www.sbs.gob.pe/app/spp/empleadores/comisiones_spp/Paginas/comision_prima.aspx
A18: Prima (flujo) | B18: 0.1 | C18: 0.016 | D18: 0.0137 | E18: https://www.sbs.gob.pe/app/spp/empleadores/comisiones_spp/Paginas/comision_prima.aspx
A19: Profuturo (flujo) | B19: 0.1 | C19: 0.0169 | D19: 0.0137 | E19: https://www.sbs.gob.pe/app/spp/empleadores/comisiones_spp/Paginas/comision_prima.aspx
A22: Amarillo = editable. Casos 1–4: RMV 1230 y AFP Ejemplo. AFP reales: modalidad flujo, devengue octubre 2026. No se aplica tope de seguro ni base mínima EsSalud por simplificación de la guía. No se modela comisión sobre saldo ni renta de quinta.
A26: Dato | B26: Valor | C26: Fuente | D26: Alcance | E26: Consulta
A27: RMV | B27: 1230; desde 01/10/2026 según guía | C27: https://busquedas.elperuano.pe/dispositivo/NL/2559163-1 | D27: D.S. 015-2026-TR; índice oficial localizado; ver fuentes.md | E27: 2026-10-26
A28: Asignación familiar | B28: 10% RMV = 123 | C28: https://www.gob.pe/institucion/mtpe/noticias/601761-quienes-tienen-derecho-a-percibir-la-asignacion-familiar | D28: Ley 25129; no prorratear en este laboratorio | E28: 2026-10-26
A29: ONP | B29: 13% | C29: https://www.gob.pe/institucion/onp/noticias/1190488-como-saber-si-tu-empleador-esta-pagando-tus-aportes-al-snp | D29: D.L. 19990 | E29: 2026-10-26
A30: EsSalud | B30: 9% | C30: https://www.sunat.gob.pe/legislacion/oficios/2007/oficios/i0032007.htm | D30: Ley 26790; la guía excluye base mínima | E30: 2026-10-26
A31: Horas extras | B31: 25% y 35% | C31: https://www.gob.pe/institucion/sunafil/noticias/1100081-conoce-las-diferencias-entre-trabajo-forzoso-y-trabajo-en-sobretiempo | D31: D.S. 007-2002-TR; horas ingresadas por tramo | E31: 2026-10-26
A32: AFP Ejemplo | B32: 10%; 1.60%; 1.35% | C32: Actividad_Grupo_B.docx, sección 4 | D32: Tasas ficticias de prueba, no tasas SBS | E32: 2026-10-26
A33: AFP reales: flujo | B33: Habitat 1.47%; Integra 1.55%; Prima 1.60%; Profuturo 1.69% | C33: https://www.sbs.gob.pe/app/spp/empleadores/comisiones_spp/Paginas/comision_prima.aspx | D33: Fondo 10%; seguro 1.37%; devengue 2026-10 | E33: 2026-10-26
A34: Oferta propia | B34: 3500–4000 mensuales; se toma 3500 | C34: https://pe.indeed.com/viewjob?jk=1a5d74a196f5ecab | D34: Desarrollador Full Stack; solo sueldo publicado, personas ficticias | E34: 2026-10-26
A35: Base mensual y jornada | B35: 30 días; 8 horas | C35: Actividad_Grupo_B.docx, sección 4 | D35: Convención académica | E35: 2026-10-26
A36: Redondeo | B36: 2 decimales por concepto antes de sumar | C36: Actividad_Grupo_B.docx, sección 4 | D36: Mitades alejándose de cero; valor hora sin redondeo previo | E36: 2026-10-26

Sheet Boleta
A1: BOLETA DE EJEMPLO · DEL SUELDO AL NETO
A2: Edita amarillo. Fórmulas en B; texto visible en C. Sin renta de quinta categoría.
A3: Entrada | B3: Valor editable | C3: Regla | D3: Ayuda
A4: Sueldo básico | B4: 2500 | C4: Mayor que 0; hasta 2 decimales
A5: Días laborados | B5: 30 | C5: Entero de 1 a 30
A6: ¿Tiene hijos? | B6: No | C6: No / Sí
A7: Sistema | B7: ONP | C7: ONP / AFP
A8: AFP | B8: Ejemplo | C8: Solo se utiliza si eliges AFP
A9: Horas extras 25% | B9: 0 | C9: No negativas; hasta 2 decimales
A10: Horas extras 35% | B10: 0 | C10: No negativas; hasta 2 decimales
A11: Adelantos | B11: 0 | C11: No negativos; hasta 2 decimales
A13: Validación | B13: =IFERROR(IF(AND(ISNUMBER(B4),B4>0,B4<=100000000,ROUND(B4,2)=B4,ISNUMBER(B5),B5=INT(B5),B5>=1,B5<=30,OR(B6="No",B6="Sí"),OR(B7="ONP",B7="AFP"),OR(B7="ONP",COUNTIF(ListaAFP,B8)=1),ISNUMBER(B9),B9>=0,B9<=10000,ROUND(B9,2)=B9,ISNUMBER(B10),B10>=0,B10<=10000,ROUND(B10,2)=B10,ISNUMBER(B11),B11>=0,B11<=100000000,ROUND(B11,2)=B11),"OK","Datos inválidos: revisa las reglas de entrada"),"Datos inválidos: revisa las reglas de entrada") -> OK
A14: Los campos numéricos son obligatorios. Si pegas datos inválidos, se oculta el cálculo.
A16: Concepto | B16: Monto (S/) | C16: Fórmula visible | D16: Bloque
A17: Sueldo computable | B17: =IF($B$13="OK",ROUND(ROUND(B4/DiasMes*B5*100,8),0)/100,"") -> 2500 | C17: =_xlfn.FORMULATEXT(B17) -> =IF($B$13="OK",ROUND(ROUND(B4/DiasMes*B5*100,8),0)/100,"") | D17: Remuneraciones
A18: Asignación familiar | B18: =IF($B$13="OK",IF(B6="Sí",ROUND(RMV*TasaAF,2),0),"") -> 0 | C18: =_xlfn.FORMULATEXT(B18) -> =IF($B$13="OK",IF(B6="Sí",ROUND(RMV*TasaAF,2),0),"") | D18: Remuneraciones
A19: Horas extras 25% | B19: =IF($B$13="OK",ROUND(ROUND(B4/DiasMes/HorasDia*Factor25*B9*100,8),0)/100,"") -> 0 | C19: =_xlfn.FORMULATEXT(B19) -> =IF($B$13="OK",ROUND(ROUND(B4/DiasMes/HorasDia*Factor25*B9*100,8),0)/100,"") | D19: Remuneraciones
A20: Horas extras 35% | B20: =IF($B$13="OK",ROUND(ROUND(B4/DiasMes/HorasDia*Factor35*B10*100,8),0)/100,"") -> 0 | C20: =_xlfn.FORMULATEXT(B20) -> =IF($B$13="OK",ROUND(ROUND(B4/DiasMes/HorasDia*Factor35*B10*100,8),0)/100,"") | D20: Remuneraciones
A21: Total remuneraciones | B21: =IF($B$13="OK",SUM(B17:B20),"") -> 2500 | C21: =_xlfn.FORMULATEXT(B21) -> =IF($B$13="OK",SUM(B17:B20),"") | D21: Remuneraciones
A22: ONP | B22: =IF($B$13="OK",IF(B7="ONP",ROUND(B21*TasaONP,2),0),"") -> 325 | C22: =_xlfn.FORMULATEXT(B22) -> =IF($B$13="OK",IF(B7="ONP",ROUND(B21*TasaONP,2),0),"") | D22: Retenciones / descuentos
A23: AFP fondo | B23: =IF($B$13="OK",IF(B7="AFP",ROUND(B21*VLOOKUP(B8,'Parámetros'!$A$15:$D$19,2,FALSE),2),0),"") -> 0 | C23: =_xlfn.FORMULATEXT(B23) -> =IF($B$13="OK",IF(B7="AFP",ROUND(B21*VLOOKUP(B8,'Parámetros'!$A$15:$D$19,2,FALSE),2),0),"") | D23: Retenciones / descuentos
A24: AFP comisión | B24: =IF($B$13="OK",IF(B7="AFP",ROUND(B21*VLOOKUP(B8,'Parámetros'!$A$15:$D$19,3,FALSE),2),0),"") -> 0 | C24: =_xlfn.FORMULATEXT(B24) -> =IF($B$13="OK",IF(B7="AFP",ROUND(B21*VLOOKUP(B8,'Parámetros'!$A$15:$D$19,3,FALSE),2),0),"") | D24: Retenciones / descuentos
A25: AFP seguro | B25: =IF($B$13="OK",IF(B7="AFP",ROUND(B21*VLOOKUP(B8,'Parámetros'!$A$15:$D$19,4,FALSE),2),0),"") -> 0 | C25: =_xlfn.FORMULATEXT(B25) -> =IF($B$13="OK",IF(B7="AFP",ROUND(B21*VLOOKUP(B8,'Parámetros'!$A$15:$D$19,4,FALSE),2),0),"") | D25: Retenciones / descuentos
A26: Adelantos | B26: =IF($B$13="OK",B11,"") -> 0 | C26: =_xlfn.FORMULATEXT(B26) -> =IF($B$13="OK",B11,"") | D26: Retenciones / descuentos
A27: Total descuentos | B27: =IF($B$13="OK",SUM(B22:B26),"") -> 325 | C27: =_xlfn.FORMULATEXT(B27) -> =IF($B$13="OK",SUM(B22:B26),"") | D27: Retenciones / descuentos
A28: Neto a pagar | B28: =IF($B$13="OK",B21-B27,"") -> 2175 | C28: =_xlfn.FORMULATEXT(B28) -> =IF($B$13="OK",B21-B27,"") | D28: Neto
A29: EsSalud | B29: =IF($B$13="OK",ROUND(B21*TasaEsSalud,2),"") -> 225 | C29: =_xlfn.FORMULATEXT(B29) -> =IF($B$13="OK",ROUND(B21*TasaEsSalud,2),"") | D29: Empleador
A30: Costo empleador | B30: =IF($B$13="OK",B21+B29,"") -> 2725 | C30: =_xlfn.FORMULATEXT(B30) -> =IF($B$13="OK",B21+B29,"") | D30: Empleador
A32: EsSalud se informa aparte: no reduce el neto. Valor hora no se redondea antes de calcular cada tramo. Un neto negativo señala adelantos excesivos; no se reemplaza por cero.

Sheet Casos
A1: CASOS · CONTROL CRUZADO CON SWIFT
A2: Filas 4–7: guía. Filas 8–10: oferta y sensibilidades, no resultados de compañeros. Editar entradas invalida el contraste original.
A3: Caso | B3: Sueldo | C3: Días | D3: Hijos | E3: Sistema | F3: AFP | G3: HE25 | H3: HE35 | I3: Adelanto | J3: Sueldo computable | K3: Asignación familiar | L3: Horas extras 25% | M3: Horas extras 35% | N3: Total remuneraciones | O3: ONP | P3: AFP fondo | Q3: AFP comisión | R3: AFP seguro | S3: Adelantos | T3: Total descuentos | U3: Neto a pagar | V3: EsSalud | W3: Costo empleador | X3: Neto oficial | Y3: Contraste guía | Z3: Neto / remuneraciones | AA3: Referencia
A4: Caso 1 | B4: 2500 | C4: 30 | D4: No | E4: ONP | F4: Ejemplo | G4: 0 | H4: 0 | I4: 0 | J4: =ROUND(ROUND(B4/DiasMes*C4*100,8),0)/100 -> 2500 | K4: =IF(D4="Sí",ROUND(RMV*TasaAF,2),0) -> 0 | L4: =ROUND(ROUND(B4/DiasMes/HorasDia*Factor25*G4*100,8),0)/100 -> 0 | M4: =ROUND(ROUND(B4/DiasMes/HorasDia*Factor35*H4*100,8),0)/100 -> 0 | N4: =SUM(J4:M4) -> 2500 | O4: =IF(E4="ONP",ROUND(N4*TasaONP,2),0) -> 325 | P4: =IF(E4="AFP",ROUND(N4*VLOOKUP(F4,'Parámetros'!$A$15:$D$19,2,FALSE),2),0) -> 0 | Q4: =IF(E4="AFP",ROUND(N4*VLOOKUP(F4,'Parámetros'!$A$15:$D$19,3,FALSE),2),0) -> 0 | R4: =IF(E4="AFP",ROUND(N4*VLOOKUP(F4,'Parámetros'!$A$15:$D$19,4,FALSE),2),0) -> 0 | S4: =I4 -> 0 | T4: =SUM(O4:S4) -> 325 | U4: =N4-T4 -> 2175 | V4: =ROUND(N4*TasaEsSalud,2) -> 225 | W4: =N4+V4 -> 2725 | X4: 2175 | Y4: =IF(ROUND(U4-X4,2)=0,"COINCIDE","REVISAR") -> COINCIDE | Z4: =U4/N4 -> 0.87 | AA4: Guía / prueba automática
A5: Caso 2 | B5: 1800 | C5: 27 | D5: Sí | E5: ONP | F5: Ejemplo | G5: 0 | H5: 0 | I5: 0 | J5: =ROUND(ROUND(B5/DiasMes*C5*100,8),0)/100 -> 1620 | K5: =IF(D5="Sí",ROUND(RMV*TasaAF,2),0) -> 123 | L5: =ROUND(ROUND(B5/DiasMes/HorasDia*Factor25*G5*100,8),0)/100 -> 0 | M5: =ROUND(ROUND(B5/DiasMes/HorasDia*Factor35*H5*100,8),0)/100 -> 0 | N5: =SUM(J5:M5) -> 1743 | O5: =IF(E5="ONP",ROUND(N5*TasaONP,2),0) -> 226.59 | P5: =IF(E5="AFP",ROUND(N5*VLOOKUP(F5,'Parámetros'!$A$15:$D$19,2,FALSE),2),0) -> 0 | Q5: =IF(E5="AFP",ROUND(N5*VLOOKUP(F5,'Parámetros'!$A$15:$D$19,3,FALSE),2),0) -> 0 | R5: =IF(E5="AFP",ROUND(N5*VLOOKUP(F5,'Parámetros'!$A$15:$D$19,4,FALSE),2),0) -> 0 | S5: =I5 -> 0 | T5: =SUM(O5:S5) -> 226.59 | U5: =N5-T5 -> 1516.41 | V5: =ROUND(N5*TasaEsSalud,2) -> 156.87 | W5: =N5+V5 -> 1899.87 | X5: 1516.41 | Y5: =IF(ROUND(U5-X5,2)=0,"COINCIDE","REVISAR") -> COINCIDE | Z5: =U5/N5 -> 0.87 | AA5: Guía / prueba automática
A6: Caso 3 | B6: 3000 | C6: 30 | D6: Sí | E6: AFP | F6: Ejemplo | G6: 4 | H6: 4 | I6: 200 | J6: =ROUND(ROUND(B6/DiasMes*C6*100,8),0)/100 -> 3000 | K6: =IF(D6="Sí",ROUND(RMV*TasaAF,2),0) -> 123 | L6: =ROUND(ROUND(B6/DiasMes/HorasDia*Factor25*G6*100,8),0)/100 -> 62.5 | M6: =ROUND(ROUND(B6/DiasMes/HorasDia*Factor35*H6*100,8),0)/100 -> 67.5 | N6: =SUM(J6:M6) -> 3253 | O6: =IF(E6="ONP",ROUND(N6*TasaONP,2),0) -> 0 | P6: =IF(E6="AFP",ROUND(N6*VLOOKUP(F6,'Parámetros'!$A$15:$D$19,2,FALSE),2),0) -> 325.3 | Q6: =IF(E6="AFP",ROUND(N6*VLOOKUP(F6,'Parámetros'!$A$15:$D$19,3,FALSE),2),0) -> 52.05 | R6: =IF(E6="AFP",ROUND(N6*VLOOKUP(F6,'Parámetros'!$A$15:$D$19,4,FALSE),2),0) -> 43.92 | S6: =I6 -> 200 | T6: =SUM(O6:S6) -> 621.27 | U6: =N6-T6 -> 2631.73 | V6: =ROUND(N6*TasaEsSalud,2) -> 292.77 | W6: =N6+V6 -> 3545.77 | X6: 2631.73 | Y6: =IF(ROUND(U6-X6,2)=0,"COINCIDE","REVISAR") -> COINCIDE | Z6: =U6/N6 -> 0.80901629 | AA6: Guía / prueba automática
A7: Caso 4 | B7: 4200 | C7: 24 | D7: Sí | E7: AFP | F7: Ejemplo | G7: 2 | H7: 2 | I7: 100 | J7: =ROUND(ROUND(B7/DiasMes*C7*100,8),0)/100 -> 3360 | K7: =IF(D7="Sí",ROUND(RMV*TasaAF,2),0) -> 123 | L7: =ROUND(ROUND(B7/DiasMes/HorasDia*Factor25*G7*100,8),0)/100 -> 43.75 | M7: =ROUND(ROUND(B7/DiasMes/HorasDia*Factor35*H7*100,8),0)/100 -> 47.25 | N7: =SUM(J7:M7) -> 3574 | O7: =IF(E7="ONP",ROUND(N7*TasaONP,2),0) -> 0 | P7: =IF(E7="AFP",ROUND(N7*VLOOKUP(F7,'Parámetros'!$A$15:$D$19,2,FALSE),2),0) -> 357.4 | Q7: =IF(E7="AFP",ROUND(N7*VLOOKUP(F7,'Parámetros'!$A$15:$D$19,3,FALSE),2),0) -> 57.18 | R7: =IF(E7="AFP",ROUND(N7*VLOOKUP(F7,'Parámetros'!$A$15:$D$19,4,FALSE),2),0) -> 48.25 | S7: =I7 -> 100 | T7: =SUM(O7:S7) -> 562.83 | U7: =N7-T7 -> 3011.17 | V7: =ROUND(N7*TasaEsSalud,2) -> 321.66 | W7: =N7+V7 -> 3895.66 | Y7: Calculado; sin respuesta oficial | Z7: =U7/N7 -> 0.84252098 | AA7: Guía / prueba automática
A8: Propio: oferta 3500 ONP | B8: 3500 | C8: 30 | D8: No | E8: ONP | F8: Ejemplo | G8: 0 | H8: 0 | I8: 0 | J8: =ROUND(ROUND(B8/DiasMes*C8*100,8),0)/100 -> 3500 | K8: =IF(D8="Sí",ROUND(RMV*TasaAF,2),0) -> 0 | L8: =ROUND(ROUND(B8/DiasMes/HorasDia*Factor25*G8*100,8),0)/100 -> 0 | M8: =ROUND(ROUND(B8/DiasMes/HorasDia*Factor35*H8*100,8),0)/100 -> 0 | N8: =SUM(J8:M8) -> 3500 | O8: =IF(E8="ONP",ROUND(N8*TasaONP,2),0) -> 455 | P8: =IF(E8="AFP",ROUND(N8*VLOOKUP(F8,'Parámetros'!$A$15:$D$19,2,FALSE),2),0) -> 0 | Q8: =IF(E8="AFP",ROUND(N8*VLOOKUP(F8,'Parámetros'!$A$15:$D$19,3,FALSE),2),0) -> 0 | R8: =IF(E8="AFP",ROUND(N8*VLOOKUP(F8,'Parámetros'!$A$15:$D$19,4,FALSE),2),0) -> 0 | S8: =I8 -> 0 | T8: =SUM(O8:S8) -> 455 | U8: =N8-T8 -> 3045 | V8: =ROUND(N8*TasaEsSalud,2) -> 315 | W8: =N8+V8 -> 3815 | Y8: Comparar con Swift | Z8: =U8/N8 -> 0.87 | AA8: https://pe.indeed.com/viewjob?jk=1a5d74a196f5ecab
A9: Sensibilidad A: 3750 AFP Prima (no compañero) | B9: 3750 | C9: 30 | D9: No | E9: AFP | F9: Prima (flujo) | G9: 0 | H9: 0 | I9: 0 | J9: =ROUND(ROUND(B9/DiasMes*C9*100,8),0)/100 -> 3750 | K9: =IF(D9="Sí",ROUND(RMV*TasaAF,2),0) -> 0 | L9: =ROUND(ROUND(B9/DiasMes/HorasDia*Factor25*G9*100,8),0)/100 -> 0 | M9: =ROUND(ROUND(B9/DiasMes/HorasDia*Factor35*H9*100,8),0)/100 -> 0 | N9: =SUM(J9:M9) -> 3750 | O9: =IF(E9="ONP",ROUND(N9*TasaONP,2),0) -> 0 | P9: =IF(E9="AFP",ROUND(N9*VLOOKUP(F9,'Parámetros'!$A$15:$D$19,2,FALSE),2),0) -> 375 | Q9: =IF(E9="AFP",ROUND(N9*VLOOKUP(F9,'Parámetros'!$A$15:$D$19,3,FALSE),2),0) -> 60 | R9: =IF(E9="AFP",ROUND(N9*VLOOKUP(F9,'Parámetros'!$A$15:$D$19,4,FALSE),2),0) -> 51.38 | S9: =I9 -> 0 | T9: =SUM(O9:S9) -> 486.38 | U9: =N9-T9 -> 3263.62 | V9: =ROUND(N9*TasaEsSalud,2) -> 337.5 | W9: =N9+V9 -> 4087.5 | Y9: Comparar con Swift | Z9: =U9/N9 -> 0.87029867 | AA9: https://pe.indeed.com/viewjob?jk=1a5d74a196f5ecab
A10: Sensibilidad B: 4000 AFP Habitat (no compañero) | B10: 4000 | C10: 30 | D10: No | E10: AFP | F10: Habitat (flujo) | G10: 0 | H10: 0 | I10: 0 | J10: =ROUND(ROUND(B10/DiasMes*C10*100,8),0)/100 -> 4000 | K10: =IF(D10="Sí",ROUND(RMV*TasaAF,2),0) -> 0 | L10: =ROUND(ROUND(B10/DiasMes/HorasDia*Factor25*G10*100,8),0)/100 -> 0 | M10: =ROUND(ROUND(B10/DiasMes/HorasDia*Factor35*H10*100,8),0)/100 -> 0 | N10: =SUM(J10:M10) -> 4000 | O10: =IF(E10="ONP",ROUND(N10*TasaONP,2),0) -> 0 | P10: =IF(E10="AFP",ROUND(N10*VLOOKUP(F10,'Parámetros'!$A$15:$D$19,2,FALSE),2),0) -> 400 | Q10: =IF(E10="AFP",ROUND(N10*VLOOKUP(F10,'Parámetros'!$A$15:$D$19,3,FALSE),2),0) -> 58.8 | R10: =IF(E10="AFP",ROUND(N10*VLOOKUP(F10,'Parámetros'!$A$15:$D$19,4,FALSE),2),0) -> 54.8 | S10: =I10 -> 0 | T10: =SUM(O10:S10) -> 513.6 | U10: =N10-T10 -> 3486.4 | V10: =ROUND(N10*TasaEsSalud,2) -> 360 | W10: =N10+V10 -> 4360 | Y10: Comparar con Swift | Z10: =U10/N10 -> 0.8716 | AA10: https://pe.indeed.com/viewjob?jk=1a5d74a196f5ecab
A11: Caso 3 con ONP | B11: 3000 | C11: 30 | D11: Sí | E11: ONP | F11: Ejemplo | G11: 4 | H11: 4 | I11: 200 | J11: =ROUND(ROUND(B11/DiasMes*C11*100,8),0)/100 -> 3000 | K11: =IF(D11="Sí",ROUND(RMV*TasaAF,2),0) -> 123 | L11: =ROUND(ROUND(B11/DiasMes/HorasDia*Factor25*G11*100,8),0)/100 -> 62.5 | M11: =ROUND(ROUND(B11/DiasMes/HorasDia*Factor35*H11*100,8),0)/100 -> 67.5 | N11: =SUM(J11:M11) -> 3253 | O11: =IF(E11="ONP",ROUND(N11*TasaONP,2),0) -> 422.89 | P11: =IF(E11="AFP",ROUND(N11*VLOOKUP(F11,'Parámetros'!$A$15:$D$19,2,FALSE),2),0) -> 0 | Q11: =IF(E11="AFP",ROUND(N11*VLOOKUP(F11,'Parámetros'!$A$15:$D$19,3,FALSE),2),0) -> 0 | R11: =IF(E11="AFP",ROUND(N11*VLOOKUP(F11,'Parámetros'!$A$15:$D$19,4,FALSE),2),0) -> 0 | S11: =I11 -> 200 | T11: =SUM(O11:S11) -> 622.89 | U11: =N11-T11 -> 2630.11 | V11: =ROUND(N11*TasaEsSalud,2) -> 292.77 | W11: =N11+V11 -> 3545.77 | Y11: Comparar con Swift | Z11: =U11/N11 -> 0.80851829 | AA11: Guía / prueba automática
A12: Caso 2 con 30 días | B12: 1800 | C12: 30 | D12: Sí | E12: ONP | F12: Ejemplo | G12: 0 | H12: 0 | I12: 0 | J12: =ROUND(ROUND(B12/DiasMes*C12*100,8),0)/100 -> 1800 | K12: =IF(D12="Sí",ROUND(RMV*TasaAF,2),0) -> 123 | L12: =ROUND(ROUND(B12/DiasMes/HorasDia*Factor25*G12*100,8),0)/100 -> 0 | M12: =ROUND(ROUND(B12/DiasMes/HorasDia*Factor35*H12*100,8),0)/100 -> 0 | N12: =SUM(J12:M12) -> 1923 | O12: =IF(E12="ONP",ROUND(N12*TasaONP,2),0) -> 249.99 | P12: =IF(E12="AFP",ROUND(N12*VLOOKUP(F12,'Parámetros'!$A$15:$D$19,2,FALSE),2),0) -> 0 | Q12: =IF(E12="AFP",ROUND(N12*VLOOKUP(F12,'Parámetros'!$A$15:$D$19,3,FALSE),2),0) -> 0 | R12: =IF(E12="AFP",ROUND(N12*VLOOKUP(F12,'Parámetros'!$A$15:$D$19,4,FALSE),2),0) -> 0 | S12: =I12 -> 0 | T12: =SUM(O12:S12) -> 249.99 | U12: =N12-T12 -> 1673.01 | V12: =ROUND(N12*TasaEsSalud,2) -> 173.07 | W12: =N12+V12 -> 2096.07 | Y12: Comparar con Swift | Z12: =U12/N12 -> 0.87 | AA12: Guía / prueba automática
A13: Redondeo valor hora | B13: 1234.56 | C13: 19 | D13: Sí | E13: AFP | F13: Ejemplo | G13: 1.25 | H13: 2.75 | I13: 10.01 | J13: =ROUND(ROUND(B13/DiasMes*C13*100,8),0)/100 -> 781.89 | K13: =IF(D13="Sí",ROUND(RMV*TasaAF,2),0) -> 123 | L13: =ROUND(ROUND(B13/DiasMes/HorasDia*Factor25*G13*100,8),0)/100 -> 8.04 | M13: =ROUND(ROUND(B13/DiasMes/HorasDia*Factor35*H13*100,8),0)/100 -> 19.1 | N13: =SUM(J13:M13) -> 932.03 | O13: =IF(E13="ONP",ROUND(N13*TasaONP,2),0) -> 0 | P13: =IF(E13="AFP",ROUND(N13*VLOOKUP(F13,'Parámetros'!$A$15:$D$19,2,FALSE),2),0) -> 93.2 | Q13: =IF(E13="AFP",ROUND(N13*VLOOKUP(F13,'Parámetros'!$A$15:$D$19,3,FALSE),2),0) -> 14.91 | R13: =IF(E13="AFP",ROUND(N13*VLOOKUP(F13,'Parámetros'!$A$15:$D$19,4,FALSE),2),0) -> 12.58 | S13: =I13 -> 10.01 | T13: =SUM(O13:S13) -> 130.7 | U13: =N13-T13 -> 801.33 | V13: =ROUND(N13*TasaEsSalud,2) -> 83.88 | W13: =N13+V13 -> 1015.91 | Y13: Comparar con Swift | Z13: =U13/N13 -> 0.85976846 | AA13: Guía / prueba automática
A14: Empate medio centavo | B14: 240.96 | C14: 30 | D14: No | E14: ONP | F14: Ejemplo | G14: 1 | H14: 0 | I14: 0 | J14: =ROUND(ROUND(B14/DiasMes*C14*100,8),0)/100 -> 240.96 | K14: =IF(D14="Sí",ROUND(RMV*TasaAF,2),0) -> 0 | L14: =ROUND(ROUND(B14/DiasMes/HorasDia*Factor25*G14*100,8),0)/100 -> 1.26 | M14: =ROUND(ROUND(B14/DiasMes/HorasDia*Factor35*H14*100,8),0)/100 -> 0 | N14: =SUM(J14:M14) -> 242.22 | O14: =IF(E14="ONP",ROUND(N14*TasaONP,2),0) -> 31.49 | P14: =IF(E14="AFP",ROUND(N14*VLOOKUP(F14,'Parámetros'!$A$15:$D$19,2,FALSE),2),0) -> 0 | Q14: =IF(E14="AFP",ROUND(N14*VLOOKUP(F14,'Parámetros'!$A$15:$D$19,3,FALSE),2),0) -> 0 | R14: =IF(E14="AFP",ROUND(N14*VLOOKUP(F14,'Parámetros'!$A$15:$D$19,4,FALSE),2),0) -> 0 | S14: =I14 -> 0 | T14: =SUM(O14:S14) -> 31.49 | U14: =N14-T14 -> 210.73 | V14: =ROUND(N14*TasaEsSalud,2) -> 21.8 | W14: =N14+V14 -> 264.02 | Y14: Comparar con Swift | Z14: =U14/N14 -> 0.86999422 | AA14: Guía / prueba automática
A15: Neto negativo permitido | B15: 2500 | C15: 30 | D15: No | E15: ONP | F15: Ejemplo | G15: 0 | H15: 0 | I15: 3000 | J15: =ROUND(ROUND(B15/DiasMes*C15*100,8),0)/100 -> 2500 | K15: =IF(D15="Sí",ROUND(RMV*TasaAF,2),0) -> 0 | L15: =ROUND(ROUND(B15/DiasMes/HorasDia*Factor25*G15*100,8),0)/100 -> 0 | M15: =ROUND(ROUND(B15/DiasMes/HorasDia*Factor35*H15*100,8),0)/100 -> 0 | N15: =SUM(J15:M15) -> 2500 | O15: =IF(E15="ONP",ROUND(N15*TasaONP,2),0) -> 325 | P15: =IF(E15="AFP",ROUND(N15*VLOOKUP(F15,'Parámetros'!$A$15:$D$19,2,FALSE),2),0) -> 0 | Q15: =IF(E15="AFP",ROUND(N15*VLOOKUP(F15,'Parámetros'!$A$15:$D$19,3,FALSE),2),0) -> 0 | R15: =IF(E15="AFP",ROUND(N15*VLOOKUP(F15,'Parámetros'!$A$15:$D$19,4,FALSE),2),0) -> 0 | S15: =I15 -> 3000 | T15: =SUM(O15:S15) -> 3325 | U15: =N15-T15 -> -825 | V15: =ROUND(N15*TasaEsSalud,2) -> 225 | W15: =N15+V15 -> 2725 | Y15: Comparar con Swift | Z15: =U15/N15 -> -0.33 | AA15: Guía / prueba automática
A16: AFP Habitat (flujo) | B16: 2345.67 | C16: 1 | D16: Sí | E16: AFP | F16: Habitat (flujo) | G16: 0.5 | H16: 0.25 | I16: 1.01 | J16: =ROUND(ROUND(B16/DiasMes*C16*100,8),0)/100 -> 78.19 | K16: =IF(D16="Sí",ROUND(RMV*TasaAF,2),0) -> 123 | L16: =ROUND(ROUND(B16/DiasMes/HorasDia*Factor25*G16*100,8),0)/100 -> 6.11 | M16: =ROUND(ROUND(B16/DiasMes/HorasDia*Factor35*H16*100,8),0)/100 -> 3.3 | N16: =SUM(J16:M16) -> 210.6 | O16: =IF(E16="ONP",ROUND(N16*TasaONP,2),0) -> 0 | P16: =IF(E16="AFP",ROUND(N16*VLOOKUP(F16,'Parámetros'!$A$15:$D$19,2,FALSE),2),0) -> 21.06 | Q16: =IF(E16="AFP",ROUND(N16*VLOOKUP(F16,'Parámetros'!$A$15:$D$19,3,FALSE),2),0) -> 3.1 | R16: =IF(E16="AFP",ROUND(N16*VLOOKUP(F16,'Parámetros'!$A$15:$D$19,4,FALSE),2),0) -> 2.89 | S16: =I16 -> 1.01 | T16: =SUM(O16:S16) -> 28.06 | U16: =N16-T16 -> 182.54 | V16: =ROUND(N16*TasaEsSalud,2) -> 18.95 | W16: =N16+V16 -> 229.55 | Y16: Comparar con Swift | Z16: =U16/N16 -> 0.86676163 | AA16: Guía / prueba automática
A17: AFP Integra (flujo) | B17: 2345.67 | C17: 1 | D17: Sí | E17: AFP | F17: Integra (flujo) | G17: 0.5 | H17: 0.25 | I17: 1.01 | J17: =ROUND(ROUND(B17/DiasMes*C17*100,8),0)/100 -> 78.19 | K17: =IF(D17="Sí",ROUND(RMV*TasaAF,2),0) -> 123 | L17: =ROUND(ROUND(B17/DiasMes/HorasDia*Factor25*G17*100,8),0)/100 -> 6.11 | M17: =ROUND(ROUND(B17/DiasMes/HorasDia*Factor35*H17*100,8),0)/100 -> 3.3 | N17: =SUM(J17:M17) -> 210.6 | O17: =IF(E17="ONP",ROUND(N17*TasaONP,2),0) -> 0 | P17: =IF(E17="AFP",ROUND(N17*VLOOKUP(F17,'Parámetros'!$A$15:$D$19,2,FALSE),2),0) -> 21.06 | Q17: =IF(E17="AFP",ROUND(N17*VLOOKUP(F17,'Parámetros'!$A$15:$D$19,3,FALSE),2),0) -> 3.26 | R17: =IF(E17="AFP",ROUND(N17*VLOOKUP(F17,'Parámetros'!$A$15:$D$19,4,FALSE),2),0) -> 2.89 | S17: =I17 -> 1.01 | T17: =SUM(O17:S17) -> 28.22 | U17: =N17-T17 -> 182.38 | V17: =ROUND(N17*TasaEsSalud,2) -> 18.95 | W17: =N17+V17 -> 229.55 | Y17: Comparar con Swift | Z17: =U17/N17 -> 0.8660019 | AA17: Guía / prueba automática
A18: AFP Prima (flujo) | B18: 2345.67 | C18: 1 | D18: Sí | E18: AFP | F18: Prima (flujo) | G18: 0.5 | H18: 0.25 | I18: 1.01 | J18: =ROUND(ROUND(B18/DiasMes*C18*100,8),0)/100 -> 78.19 | K18: =IF(D18="Sí",ROUND(RMV*TasaAF,2),0) -> 123 | L18: =ROUND(ROUND(B18/DiasMes/HorasDia*Factor25*G18*100,8),0)/100 -> 6.11 | M18: =ROUND(ROUND(B18/DiasMes/HorasDia*Factor35*H18*100,8),0)/100 -> 3.3 | N18: =SUM(J18:M18) -> 210.6 | O18: =IF(E18="ONP",ROUND(N18*TasaONP,2),0) -> 0 | P18: =IF(E18="AFP",ROUND(N18*VLOOKUP(F18,'Parámetros'!$A$15:$D$19,2,FALSE),2),0) -> 21.06 | Q18: =IF(E18="AFP",ROUND(N18*VLOOKUP(F18,'Parámetros'!$A$15:$D$19,3,FALSE),2),0) -> 3.37 | R18: =IF(E18="AFP",ROUND(N18*VLOOKUP(F18,'Parámetros'!$A$15:$D$19,4,FALSE),2),0) -> 2.89 | S18: =I18 -> 1.01 | T18: =SUM(O18:S18) -> 28.33 | U18: =N18-T18 -> 182.27 | V18: =ROUND(N18*TasaEsSalud,2) -> 18.95 | W18: =N18+V18 -> 229.55 | Y18: Comparar con Swift | Z18: =U18/N18 -> 0.86547958 | AA18: Guía / prueba automática
A19: AFP Profuturo (flujo) | B19: 2345.67 | C19: 1 | D19: Sí | E19: AFP | F19: Profuturo (flujo) | G19: 0.5 | H19: 0.25 | I19: 1.01 | J19: =ROUND(ROUND(B19/DiasMes*C19*100,8),0)/100 -> 78.19 | K19: =IF(D19="Sí",ROUND(RMV*TasaAF,2),0) -> 123 | L19: =ROUND(ROUND(B19/DiasMes/HorasDia*Factor25*G19*100,8),0)/100 -> 6.11 | M19: =ROUND(ROUND(B19/DiasMes/HorasDia*Factor35*H19*100,8),0)/100 -> 3.3 | N19: =SUM(J19:M19) -> 210.6 | O19: =IF(E19="ONP",ROUND(N19*TasaONP,2),0) -> 0 | P19: =IF(E19="AFP",ROUND(N19*VLOOKUP(F19,'Parámetros'!$A$15:$D$19,2,FALSE),2),0) -> 21.06 | Q19: =IF(E19="AFP",ROUND(N19*VLOOKUP(F19,'Parámetros'!$A$15:$D$19,3,FALSE),2),0) -> 3.56 | R19: =IF(E19="AFP",ROUND(N19*VLOOKUP(F19,'Parámetros'!$A$15:$D$19,4,FALSE),2),0) -> 2.89 | S19: =I19 -> 1.01 | T19: =SUM(O19:S19) -> 28.52 | U19: =N19-T19 -> 182.08 | V19: =ROUND(N19*TasaEsSalud,2) -> 18.95 | W19: =N19+V19 -> 229.55 | Y19: Comparar con Swift | Z19: =U19/N19 -> 0.8645774 | AA19: Guía / prueba automática
A23: PENDIENTE: resultados reales de dos compañeros (no inventados)
A24: Compañero ficticio/alias | B24: Oferta y fecha | C24: Sueldo | D24: Neto | E24: % neto/bruto | F24: Observación
A25: Por completar | E25: =IF(AND(ISNUMBER(C25),ISNUMBER(D25),C25>0),D25/C25,"") | F25: Solicitar boleta y fuente a un compañero
A26: Por completar | E26: =IF(AND(ISNUMBER(C26),ISNUMBER(D26),C26>0),D26/C26,"") | F26: Solicitar boleta y fuente a un compañero

Sheet Explicación
A1: CADA FÓRMULA EN PALABRAS
A3: Concepto | B3: Explicación sencilla | C3: Ejemplo numérico | D3: Fórmula Excel en Boleta
A4: Sueldo computable | B4: Divide el sueldo entre 30 y multiplícalo por los días trabajados. | C4: Caso 2: 1800 / 30 × 27 = 1620.00 | D4: =ROUND(ROUND(B4/DiasMes*B5*100,8),0)/100
A5: Asignación familiar | B5: Si tiene hijos, entrega el 10% de RMV completo; no lo dividas por días. | C5: Caso 2: 1230 × 10% = 123.00 | D5: =IF(B6="Sí",ROUND(RMV*TasaAF,2),0)
A6: Horas extras 25% | B6: Divide sueldo entre 30 y 8, aumenta 25% y multiplica por las horas de este tramo. | C6: Caso 3: 3000 / 30 / 8 × 1.25 × 4 = 62.50 | D6: =ROUND(ROUND(B4/DiasMes/HorasDia*Factor25*B9*100,8),0)/100
A7: Horas extras 35% | B7: Usa el valor hora sin redondear, aumenta 35% y multiplica por las horas de este tramo. | C7: Caso 3: 12.50 × 1.35 × 4 = 67.50 | D7: =ROUND(ROUND(B4/DiasMes/HorasDia*Factor35*B10*100,8),0)/100
A8: Total remuneraciones | B8: Suma sueldo computable, asignación y ambos tramos, ya redondeados. | C8: Caso 3: 3000 + 123 + 62.50 + 67.50 = 3253.00 | D8: =SUM(B17:B20)
A9: ONP | B9: Si eligió ONP, retén el 13% de todas las remuneraciones; si AFP, muestra cero. | C9: Caso 2: 1743 × 13% = 226.59 | D9: =IF(B7="ONP",ROUND(B21*TasaONP,2),0)
A10: AFP fondo | B10: Si eligió AFP, multiplica remuneraciones por tasa del fondo de la AFP elegida. | C10: Caso 3: 3253 × 10% = 325.30 | D10: =IF(B7="AFP",ROUND(B21*VLOOKUP(B8,'Parámetros'!$A$15:$D$19,2,FALSE),2),0)
A11: AFP comisión | B11: Multiplica remuneraciones por la comisión de flujo, redondeada individualmente. | C11: Caso 3: 3253 × 1.60% = 52.048 → 52.05 | D11: =IF(B7="AFP",ROUND(B21*VLOOKUP(B8,'Parámetros'!$A$15:$D$19,3,FALSE),2),0)
A12: AFP seguro | B12: Multiplica remuneraciones por la prima de seguro y redondea. | C12: Caso 3: 3253 × 1.35% = 43.9155 → 43.92 | D12: =IF(B7="AFP",ROUND(B21*VLOOKUP(B8,'Parámetros'!$A$15:$D$19,4,FALSE),2),0)
A13: Adelantos | B13: Copia el adelanto, que ya tiene como máximo dos decimales. | C13: Caso 3: 200.00 | D13: =B11
A14: Total descuentos | B14: Suma ONP o los tres aportes AFP y agrega adelantos. | C14: Caso 3: 325.30 + 52.05 + 43.92 + 200 = 621.27 | D14: =SUM(B22:B26)
... A17: Costo empleador | B17: Suma remuneraciones y EsSalud para este costo mensual simplificado. | C17: Caso 3: 3253 + 292.77 = 3545.77 | D17: =B21+B29
A19: Redondeo: 2 decimales por concepto, luego SUM. Sueldo y HE usan ROUND(ROUND(importe*100,8),0)/100: normalizar residuos a 8 decimales de céntimo y redondear a céntimos enteros. Ejemplo 1.2549999999999999 → 125.5 → 126 → 1.26. No se redondea el valor hora por separado.
A22: Lectura: revisa Parámetros → edita Boleta → examina Casos → explica cada paso. Ctrl+` alterna fórmulas; C en Boleta ya muestra FORMULATEXT. Cambiar tasas recalcula todos los casos; los esperados oficiales permanecen fijos.
A25: Análisis completo y fuentes en docs/analisis.md y docs/fuentes.md. Las sensibilidades de la oferta no sustituyen la comparación con dos compañeros, que queda pendiente de sus resultados reales.
